datazone/__init__.py
datazone/cli/__init__.py
datazone/cli/auth/__init__.py
datazone/cli/auth/configure.py
datazone/cli/auth/login.py
datazone/cli/auth/main.py
datazone/cli/dataset/__init__.py
datazone/cli/dataset/list.py
datazone/cli/dataset/main.py
datazone/cli/dataset/show.py
datazone/cli/dataset/transactions.py
datazone/cli/dataset/view/__init__.py
datazone/cli/dataset/view/create.py
datazone/cli/dataset/view/delete.py
datazone/cli/dataset/view/list.py
datazone/cli/dataset/view/main.py
datazone/cli/datazone_typer.py
datazone/cli/execution/__init__.py
datazone/cli/execution/history.py
datazone/cli/execution/list.py
datazone/cli/execution/log.py
datazone/cli/execution/main.py
datazone/cli/execution/run.py
datazone/cli/extract/__init__.py
datazone/cli/extract/create.py
datazone/cli/extract/delete.py
datazone/cli/extract/execute.py
datazone/cli/extract/history.py
datazone/cli/extract/list.py
datazone/cli/extract/main.py
datazone/cli/main.py
datazone/cli/pipeline/__init__.py
datazone/cli/pipeline/create.py
datazone/cli/pipeline/main.py
datazone/cli/repository/__init__.py
datazone/cli/repository/clone.py
datazone/cli/repository/create.py
datazone/cli/repository/deploy.py
datazone/cli/repository/list.py
datazone/cli/repository/main.py
datazone/cli/repository/pull.py
datazone/cli/repository/summary.py
datazone/cli/repository/template_loader.py
datazone/cli/repository/templates/__init__.py
datazone/cli/repository/templates/config.yml.jinja
datazone/cli/repository/templates/hello_world.py.jinja
datazone/cli/schedule/__init__.py
datazone/cli/schedule/create.py
datazone/cli/schedule/delete.py
datazone/cli/schedule/list.py
datazone/cli/schedule/main.py
datazone/cli/source/__init__.py
datazone/cli/source/create.py
datazone/cli/source/delete.py
datazone/cli/source/list.py
datazone/cli/source/main.py
datazone/cli/source/update.py
datazone/constants.py
datazone/context.py
datazone/core/__init__.py
datazone/core/common/__init__.py
datazone/core/common/config.py
datazone_northstar-0.0.22.dist-info/METADATA
datazone_northstar-0.0.22.dist-info/WHEEL
datazone_northstar-0.0.22.dist-info/entry_points.txt
datazone_northstar-0.0.22.dist-info/RECORD
