Metadata-Version: 2.1
Name: datazone-northstar
Version: 0.0.22
Summary: Datazone Northstar Client Package
Author: resulyurttakalan
Author-email: resul@datazone.co
Requires-Python: >=3.9,<4.0
Classifier: Programming Language :: Python :: 3
Classifier: Programming Language :: Python :: 3.9
Classifier: Programming Language :: Python :: 3.10
Classifier: Programming Language :: Python :: 3.11
Classifier: Programming Language :: Python :: 3.12
Requires-Dist: bson (>=0.5,<0.6)
Requires-Dist: gitpython (>=3.1.31,<4.0.0)
Requires-Dist: jinja2 (>=3.1.2,<4.0.0)
Requires-Dist: keyring (>=23.13.1,<24.0.0)
Requires-Dist: oauthlib (>=3.2.2,<4.0.0)
Requires-Dist: pandas (>=1.5.3,<2.0.0)
Requires-Dist: pyarrow (>=11.0.0,<12.0.0)
Requires-Dist: pydantic (>=1.10.6,<2.0.0)
Requires-Dist: pyspark (>=3.3.2,<4.0.0)
Requires-Dist: pyyaml (>=6.0,<7.0)
Requires-Dist: requests-oauthlib (>=1.3.1,<2.0.0)
Requires-Dist: typer[all] (>=0.7.0,<0.8.0)
